cards/__init__.py
cards/api.py
cards/cli.py
cards/db.py
cards-1.0.1.dist-info/entry_points.txt
cards-1.0.1.dist-info/LICENSE
cards-1.0.1.dist-info/WHEEL
cards-1.0.1.dist-info/METADATA
cards-1.0.1.dist-info/RECORD
